LICENSE
MANIFEST.in
README.md
setup.py
django_eca_catalogue.egg-info/PKG-INFO
django_eca_catalogue.egg-info/SOURCES.txt
django_eca_catalogue.egg-info/dependency_links.txt
django_eca_catalogue.egg-info/requires.txt
django_eca_catalogue.egg-info/top_level.txt
eca_catalogue/__init__.py
eca_catalogue/models.py
eca_catalogue/views.py
eca_catalogue/categorization/__init__.py
eca_catalogue/categorization/abstract_admin.py
eca_catalogue/categorization/abstract_models.py
eca_catalogue/categorization/tests/__init__.py
eca_catalogue/categorization/tests/models.py
eca_catalogue/material/__init__.py
eca_catalogue/material/abstract_admin.py
eca_catalogue/material/abstract_models.py
eca_catalogue/material/tests/__init__.py
eca_catalogue/material/tests/models.py
eca_catalogue/measurement/__init__.py
eca_catalogue/measurement/abstract_admin.py
eca_catalogue/measurement/abstract_models.py
eca_catalogue/measurement/tests/__init__.py
eca_catalogue/measurement/tests/models.py
eca_catalogue/product/__init__.py
eca_catalogue/product/abstract_admin.py
eca_catalogue/product/abstract_models.py
eca_catalogue/product/tests/__init__.py
eca_catalogue/product/tests/models.py
eca_catalogue/tests/__init__.py
eca_catalogue/tests/runtests.py
eca_catalogue/text/__init__.py
eca_catalogue/text/abstract_admin.py
eca_catalogue/text/abstract_models.py
eca_catalogue/text/tests/__init__.py
eca_catalogue/text/tests/factories.py
eca_catalogue/text/tests/models.py
eca_catalogue/text/tests/models_tests.py