Metadata-Version: 1.0
Name: django-eca-catalogue
Version: 0.0.2
Summary: A reusable django app providing a generic product catalog for eComerce projects
Home-page: https://github.com/byteweaver/django-eca-catalogue
Author: byteweaver
Author-email: contact@byteweaver.net
License: Copyright (c) 2012, byteweaver
